setup.py
bluedart/__init__.py
bluedart/base_service.py
bluedart/profile.py
bluedart.egg-info/PKG-INFO
bluedart.egg-info/SOURCES.txt
bluedart.egg-info/dependency_links.txt
bluedart.egg-info/requires.txt
bluedart.egg-info/top_level.txt
bluedart/services/__init__.py
bluedart/services/pickup_service.py
bluedart/services/ship_service.py