Metadata-Version: 1.1
Name: bluedart
Version: 1.0.2
Summary: Bluedart Web Services API wrapper.
Home-page: https://github.com/hornedbull/bluedart.git
Author: Vatsal Shah
Author-email: shahvatsal90@gmail.com
License: MIT
Download-URL: http://pypi.python.org/pypi/bluedart/
Keywords: bluedart soap suds wrapper rate location ship service
Platform: Platform Independent
Classifier: Development Status :: 5 - Production/Stable
Classifier: Intended Audience :: Developers
Classifier: License :: OSI Approved :: MIT License
Classifier: Natural Language :: English
Classifier: Operating System :: OS Independent
Classifier: Programming Language :: Python
Classifier: Topic :: Software Development :: Libraries :: Python Modules
Requires: suds
